DeepGlow/DGmain.py
DeepGlow/__init__.py
DeepGlow/data/model-ism-final.hdf5
DeepGlow/data/model-wind-final.hdf5
DeepGlow/data/scale_facs_ism_final.csv
DeepGlow/data/scale_facs_wind_final.csv
DeepGlow-1.1.0.dist-info/LICENSE
DeepGlow-1.1.0.dist-info/METADATA
DeepGlow-1.1.0.dist-info/WHEEL
DeepGlow-1.1.0.dist-info/top_level.txt
DeepGlow-1.1.0.dist-info/RECORD
