Metadata-Version: 2.1
Name: DeepGlow
Version: 1.1.0
Summary: A neural network emulator for BOXFIT
Home-page: https://github.com/OMBoersma/DeepGlow
Author: Oliver Boersma
Author-email: o.m.boersma@uva.nl
License: BSD 2-clause
Platform: UNKNOWN
Classifier: Development Status :: 4 - Beta
Classifier: Intended Audience :: Science/Research
Classifier: License :: OSI Approved :: BSD License
Classifier: Operating System :: POSIX :: Linux
Classifier: Operating System :: Unix
Classifier: Programming Language :: Python :: 3
Classifier: Programming Language :: Python :: 3.7
Classifier: Programming Language :: Python :: 3.8
Classifier: Programming Language :: Python :: 3.9
Classifier: Programming Language :: Python :: 3.10
Classifier: Topic :: Scientific/Engineering
Requires-Dist: tensorflow >=2.0.0
Requires-Dist: numpy
Requires-Dist: importlib.resources
Provides-Extra: quality
Requires-Dist: flake8 ; extra == 'quality'
Requires-Dist: mypy ; extra == 'quality'
Requires-Dist: types-tensorflow ; extra == 'quality'
Requires-Dist: black ; extra == 'quality'
Provides-Extra: test
Requires-Dist: pytest ; extra == 'test'
